mongol_register_parser/__init__.py
mongol_register_parser/mongol_register_parser.py
mongol_register_parser-0.1.4.dist-info/LICENSE
mongol_register_parser-0.1.4.dist-info/METADATA
mongol_register_parser-0.1.4.dist-info/WHEEL
mongol_register_parser-0.1.4.dist-info/top_level.txt
mongol_register_parser-0.1.4.dist-info/RECORD
