Metadata-Version: 2.1
Name: mongol_register_parser
Version: 0.1.4
Summary: mongol register parser
Home-page: https://github.com/ganbaaelmer/mongol_register_parser.git
Author: Ganbaatar Bold
Author-email: elmerganbaa <elmerganbaa@gmail.com>
Project-URL: Homepage, https://github.com/ganbaaelmer/mongol_register_parser
Project-URL: Issues, https://github.com/ganbaaelmer/mongol_register_parser
Classifier: Programming Language :: Python :: 3
Classifier: License :: OSI Approved :: MIT License
Classifier: Operating System :: OS Independent
Requires-Python: >=3.6
License-File: LICENSE
